key_management_client/__init__.py
key_management_client/api_client.py
key_management_client/configuration.py
key_management_client/rest.py
key_management_client/api/__init__.py
key_management_client/api/configurations_api.py
key_management_client/api/entities_api.py
key_management_client/api/external_reference_api.py
key_management_client/api/external_references_api.py
key_management_client/api/organizations_api.py
key_management_client/api/tool_types_api.py
key_management_client/api/tools_api.py
key_management_client/models/__init__.py
key_management_client/models/configuration_.py
key_management_client/models/entity_.py
key_management_client/models/external_reference_.py
key_management_client/models/organization_.py
key_management_client/models/tool_.py
key_management_client/models/tool_type_.py
test/__init__.py
test/test_configuration_.py
test/test_configurations_api.py
test/test_entities_api.py
test/test_entity_.py
test/test_external_reference_.py
test/test_external_reference_api.py
test/test_external_references_api.py
test/test_organization_.py
test/test_organizations_api.py
test/test_tool_.py
test/test_tool_type_.py
test/test_tool_types_api.py
test/test_tools_api.py
key_management_client-1.0.25.dist-info/METADATA
key_management_client-1.0.25.dist-info/WHEEL
key_management_client-1.0.25.dist-info/top_level.txt
key_management_client-1.0.25.dist-info/RECORD
