Metadata-Version: 2.1
Name: key-management-client
Version: 1.0.25
Summary: Key Manager API
Home-page: UNKNOWN
Author: UNKNOWN
Author-email: paulossjunior@gmail.com
License: UNKNOWN
Keywords: Swagger,Key Manager API
Platform: UNKNOWN
Requires-Dist: certifi (>=2017.4.17)
Requires-Dist: python-dateutil (>=2.1)
Requires-Dist: six (>=1.10)
Requires-Dist: urllib3 (>=1.23)
